{
 "actions": [],
 "allow_rename": 1,
 "creation": "2023-11-18 08:03:19.112521",
 "doctype": "DocType",
 "editable_grid": 1,
 "engine": "InnoDB",
 "field_order": [
  "item_name",
  "uom",
  "qty"
 ],
 "fields": [
  {
   "fieldname": "item_name",
   "fieldtype": "Link",
   "in_list_view": 1,
   "label": "Item Name",
   "options": "Item",
   "reqd": 1
  },
  {
   "fieldname": "uom",
   "fieldtype": "Link",
   "in_list_view": 1,
   "label": "UOM",
   "options": "UOM"
  },
  {
   "fieldname": "qty",
   "fieldtype": "Float",
   "in_list_view": 1,
   "label": "Qty"
  }
 ],
 "index_web_pages_for_search": 1,
 "istable": 1,
 "links": [],
 "modified": "2023-11-18 08:06:24.989591",
 "modified_by": "Administrator",
 "module": "Aabha Homes",
 "name": "Material Consumption Details",
 "owner": "Administrator",
 "permissions": [],
 "sort_field": "modified",
 "sort_order": "DESC",
 "states": []
}